localemembers/__init__.py
localemembers/gui.py
localemembers/locale_members.py
tests/__init__.py
tests/test_locale_members.py
localemembers-1.1.1.dist-info/LICENSE
localemembers-1.1.1.dist-info/METADATA
localemembers-1.1.1.dist-info/WHEEL
localemembers-1.1.1.dist-info/entry_points.txt
localemembers-1.1.1.dist-info/top_level.txt
localemembers-1.1.1.dist-info/RECORD
