Metadata-Version: 2.1
Name: localemembers
Version: 1.1.1
Summary: A Python module to detect and format system localization information.
Home-page: https://github.com/yourusername/localemembers
Author: Your Name
Author-email: your.email@example.com
Classifier: Programming Language :: Python :: 3
Classifier: License :: OSI Approved :: MIT License
Classifier: Operating System :: OS Independent
Requires-Python: >=3.6
License-File: LICENSE
Requires-Dist: PyQt5
